{
  "name": "PAUSE",
  "imagePath": "",
  "assets": [
    {
      "type": "image",
      "name": "bannerGamePaused2",
      "imagePath": "/buttonsV2/bannerGamePaused2.png",
      "x": 16.042, 
      "y": 0,
      "imageScale": 0.666,
      "renderPriority": 1
    },
    {
      "type": "image",
      "name": "bannerGamePaused",
      "imagePath": "/buttonsV2/bannerGamePaused.png",
      "x": 0,
      "y": 0,
      "imageScale": 0.666,
      "renderPriority": 1
    },
    {
      "type": "image",
      "name": "resume",
      "imagePath": "/buttonsV2/resume.png",
      "x": 20.052,
      "y": 17.222,
      "imageScale": 0.666,
      "renderPriority": 1
    },
    {
      "type": "image",
      "name": "restart",
      "imagePath": "/buttonsV2/restart.png",
      "x": 30.395,
      "y": 45.093,
      "imageScale": 0.666,
      "renderPriority": 1
    },
    {
      "type": "image",
      "name": "returnToMainMenu",
      "imagePath": "/buttonsV2/quit.png",
      "x": 17.531,
      "y": 70.556,
      "imageScale": 0.666,
      "renderPriority": 1
    }
  ]
}
